kestrel_datasource_stixshifter/__init__.py
kestrel_datasource_stixshifter/cli.py
kestrel_datasource_stixshifter/config.py
kestrel_datasource_stixshifter/connector.py
kestrel_datasource_stixshifter/diagnosis.py
kestrel_datasource_stixshifter/interface.py
kestrel_datasource_stixshifter/multiproc.py
kestrel_datasource_stixshifter/query.py
kestrel_datasource_stixshifter/subquery.py
kestrel_datasource_stixshifter/worker/__init__.py
kestrel_datasource_stixshifter/worker/translator.py
kestrel_datasource_stixshifter/worker/transmitter.py
kestrel_datasource_stixshifter/worker/utils.py
kestrel_datasource_stixshifter-1.8.5.dist-info/METADATA
kestrel_datasource_stixshifter-1.8.5.dist-info/WHEEL
kestrel_datasource_stixshifter-1.8.5.dist-info/entry_points.txt
kestrel_datasource_stixshifter-1.8.5.dist-info/top_level.txt
kestrel_datasource_stixshifter-1.8.5.dist-info/RECORD
