Metadata-Version: 2.1
Name: kestrel_datasource_stixshifter
Version: 1.8.5
Summary: Kestrel STIX-shifter Datasource Interface
Maintainer-email: Xiaokui Shu <xiaokui.shu@ibm.com>, Paul Coccoli <pcoccoli@us.ibm.com>
License: Apache 2.0 License
Project-URL: Homepage, https://github.com/opencybersecurityalliance/kestrel-lang
Project-URL: Documentation, https://kestrel.readthedocs.io/
Project-URL: Repository, https://github.com/opencybersecurityalliance/kestrel-lang.git
Keywords: kestrel,datasource,interface,STIX-shifter
Classifier: Topic :: Security
Classifier: Operating System :: OS Independent
Classifier: Development Status :: 4 - Beta
Classifier: Programming Language :: Python :: 3
Requires-Python: >=3.8
Requires-Dist: kestrel_core>=1.8.2
Requires-Dist: lxml==4.9.4
Requires-Dist: requests>=2.31.0
Requires-Dist: nest-asyncio>=1.6.0
Requires-Dist: stix-shifter==7.0.7
Requires-Dist: stix-shifter-utils==7.0.7
Provides-Extra: test
Requires-Dist: pytest; extra == "test"
Requires-Dist: stix-shifter-modules-elastic-ecs; extra == "test"
